cv/__init__.py
cv/cv.py
luyuxi-0.1.1.dist-info/LICENSE
luyuxi-0.1.1.dist-info/METADATA
luyuxi-0.1.1.dist-info/WHEEL
luyuxi-0.1.1.dist-info/top_level.txt
luyuxi-0.1.1.dist-info/RECORD
