Metadata-Version: 2.1
Name: luyuxi
Version: 0.1.1
Summary: My personal package
Author: divided7
Author-email: divided.by.07@gmail.com
License-File: LICENSE
Requires-Dist: tqdm
Requires-Dist: opencv-python
Requires-Dist: numpy
Requires-Dist: matplotlib
